django_keygen/__init__.py
django_keygen/exceptions.py
django_keygen/management/__init__.py
django_keygen/management/commands/__init__.py
django_keygen/management/commands/keygen.py
tests/__init__.py
tests/test_KeyGen.py
tests/management/__init__.py
tests/management/commands/__init__.py
tests/management/commands/test_Command.py
django_keygen-1.1.1.dist-info/LICENSE.txt
django_keygen-1.1.1.dist-info/METADATA
django_keygen-1.1.1.dist-info/WHEEL
django_keygen-1.1.1.dist-info/top_level.txt
django_keygen-1.1.1.dist-info/RECORD
